styleio/__init__.py
styleio/codes.py
styleio/style.py
styleio-0.0.3.dist-info/METADATA
styleio-0.0.3.dist-info/WHEEL
styleio-0.0.3.dist-info/licenses/LICENSE
styleio-0.0.3.dist-info/RECORD
