Metadata-Version: 2.4
Name: styleio
Version: 0.0.3
Summary: A simple output styler in Python
Project-URL: homepage, https://github.com/anaphan1/styleio/
Project-URL: issues, https://github.com/anaphan1/styleio/issues
License-File: LICENSE
Classifier: License :: OSI Approved :: MIT License
Classifier: Operating System :: OS Independent
Classifier: Programming Language :: Python :: 3
Requires-Python: >=3.6
